examples/__init__.py
examples/cifar/__init__.py
examples/cifar/analyze.py
examples/cifar/detect_mislabeled_dataset.py
examples/cifar/half_precision_analysis.py
examples/cifar/inspect_factors.py
examples/cifar/pipeline.py
examples/cifar/train.py
examples/dailymail/__init__.py
examples/dailymail/analyze.py
examples/dailymail/inspect_examples.py
examples/dailymail/pipeline.py
examples/dailymail/train.py
examples/glue/__init__.py
examples/glue/analyze.py
examples/glue/evaluate_lds.py
examples/glue/half_precision_analysis.py
examples/glue/pipeline.py
examples/glue/run_counterfactual.py
examples/glue/train.py
examples/imagenet/__init__.py
examples/imagenet/analyze.py
examples/imagenet/ddp_analyze.py
examples/imagenet/pipeline.py
examples/imagenet/query_batching_analysis.py
examples/openwebtext/__init__.py
examples/openwebtext/compute_scores.py
examples/openwebtext/fit_factors.py
examples/openwebtext/generate.py
examples/openwebtext/inpsect_factors.py
examples/openwebtext/inspect_scores.py
examples/openwebtext/pipeline.py
examples/openwebtext/task.py
examples/swag/__init__.py
examples/swag/analyze.py
examples/swag/evaluate_lds.py
examples/swag/influence_analysis.py
examples/swag/pipeline.py
examples/swag/train.py
examples/uci/__init__.py
examples/uci/analyze.py
examples/uci/pipeline.py
examples/uci/train.py
examples/wikitext/__init__.py
examples/wikitext/analyze.py
examples/wikitext/evaluate_lds.py
examples/wikitext/half_precision_analysis.py
examples/wikitext/pipeline.py
examples/wikitext/run_counterfactual.py
examples/wikitext/tokenwise_analysis.py
examples/wikitext/train.py
kronfluence/__init__.py
kronfluence/analyzer.py
kronfluence/arguments.py
kronfluence/task.py
kronfluence/version.py
kronfluence/computer/__init__.py
kronfluence/computer/computer.py
kronfluence/computer/factor_computer.py
kronfluence/computer/score_computer.py
kronfluence/factor/__init__.py
kronfluence/factor/config.py
kronfluence/factor/covariance.py
kronfluence/factor/eigen.py
kronfluence-1.0.1.dist-info/LICENSE
kronfluence-1.0.1.dist-info/METADATA
kronfluence-1.0.1.dist-info/WHEEL
kronfluence-1.0.1.dist-info/top_level.txt
kronfluence-1.0.1.dist-info/RECORD
