Metadata-Version: 2.1
Name: kronfluence
Version: 1.0.1
Summary: Influence Functions with (Eigenvalue-corrected) Kronecker-factored Approximate Curvature
License: Apache-2.0
Keywords: Training Data Attribution,Influence Functions
Classifier: Development Status :: 4 - Beta
Classifier: Intended Audience :: Developers
Classifier: Intended Audience :: Science/Research
Classifier: License :: OSI Approved :: Apache Software License
Classifier: Operating System :: OS Independent
Classifier: Programming Language :: Python :: 3.9
Classifier: Programming Language :: Python :: 3.10
Classifier: Programming Language :: Python :: 3.11
Classifier: Programming Language :: Python :: 3.12
Classifier: Topic :: Scientific/Engineering :: Artificial Intelligence
Requires-Python: >=3.9.0
License-File: LICENSE
Requires-Dist: torch >=2.1.0
Requires-Dist: torchvision >=0.16.0
Requires-Dist: accelerate >=0.31.0
Requires-Dist: einops >=0.8.0
Requires-Dist: einconv >=0.1.0
Requires-Dist: opt-einsum >=3.3.0
Requires-Dist: safetensors >=0.4.2
Requires-Dist: tqdm >=4.66.4
Provides-Extra: dev
Requires-Dist: torch >=2.1.0 ; extra == 'dev'
Requires-Dist: torchvision >=0.16.0 ; extra == 'dev'
Requires-Dist: accelerate >=0.31.0 ; extra == 'dev'
Requires-Dist: einops >=0.8.0 ; extra == 'dev'
Requires-Dist: einconv >=0.1.0 ; extra == 'dev'
Requires-Dist: opt-einsum >=3.3.0 ; extra == 'dev'
Requires-Dist: scikit-learn >=1.4.0 ; extra == 'dev'
Requires-Dist: safetensors >=0.4.2 ; extra == 'dev'
Requires-Dist: tqdm >=4.66.4 ; extra == 'dev'
Requires-Dist: datasets >=2.20.0 ; extra == 'dev'
Requires-Dist: transformers >=4.42.0 ; extra == 'dev'
Requires-Dist: isort ==5.13.2 ; extra == 'dev'
Requires-Dist: pylint ==3.2.3 ; extra == 'dev'
Requires-Dist: pytest ==8.2.2 ; extra == 'dev'
Requires-Dist: ruff ==0.4.0 ; extra == 'dev'
